std_daq_client/__init__.py
std_daq_client/cli.py
std_daq_client/client.py
std_daq_client-1.3.5.dist-info/METADATA
std_daq_client-1.3.5.dist-info/WHEEL
std_daq_client-1.3.5.dist-info/entry_points.txt
std_daq_client-1.3.5.dist-info/top_level.txt
std_daq_client-1.3.5.dist-info/RECORD
