Metadata-Version: 2.1
Name: std-daq-client
Version: 1.3.5
Summary: Python client for standard-daq
Home-page: https://github.com/paulscherrerinstitute/std_daq_service
Author: Paul Scherrer Institute
Requires-Dist: requests
